rupauli/__init__.py
rupauli-0.1.0.dist-info/licenses/LICENCE
rupauli-0.1.0.dist-info/METADATA
rupauli-0.1.0.dist-info/WHEEL
rupauli-0.1.0.dist-info/top_level.txt
rupauli-0.1.0.dist-info/RECORD
