Metadata-Version: 2.4
Name: rupauli
Version: 0.1.0
Summary: Efficient quantum operator processing library from Quantinuum
Author-email: Robert Anderson <robert.anderson@quantinuum.com>
License: Apache2.0
Project-URL: Homepage, https://github.com/Quantinuum/rupauli
Requires-Python: >=3.8
License-File: LICENCE
Dynamic: license-file
